wiki_futures/__init__.py
wiki_futures/dispatcher.py
wiki_futures-0.0.1.dist-info/LICENSE
wiki_futures-0.0.1.dist-info/METADATA
wiki_futures-0.0.1.dist-info/WHEEL
wiki_futures-0.0.1.dist-info/top_level.txt
wiki_futures-0.0.1.dist-info/RECORD
