Metadata-Version: 2.1
Name: wiki-futures
Version: 0.0.1
Summary: Asynchronously downloads Wikipedia pages
Home-page: https://github.com/AndrewRPorter/wiki-futures
Author: Andrew Porter
Author-email: porter.r.andrew@gmail.com
License: MIT License
Download-URL: https://github.com/AndrewRPorter/wiki-futures/releases
Platform: UNKNOWN
Requires-Dist: setuptools
Requires-Dist: requests
Requires-Dist: requests-futures
